hypercube/__init__.py
hypercube/array_factory.py
hypercube/base_cube.py
hypercube/dims.py
hypercube/version.py
hypercube/tests/__init__.py
hypercube/tests/run_tests.py
hypercube/tests/test_cube.py
hypercube/util/__init__.py
hypercube-0.3.6.dist-info/licenses/LICENSE
hypercube-0.3.6.dist-info/METADATA
hypercube-0.3.6.dist-info/WHEEL
hypercube-0.3.6.dist-info/top_level.txt
hypercube-0.3.6.dist-info/zip-safe
hypercube-0.3.6.dist-info/RECORD
